textfun/Ejercicios Estructuras Selección.py
textfun/EjerciciosAmpliacionSeleccionRepeticion.py
textfun/EjerciciosRepeticionSaltosBasicos.py
textfun/__init__.py
seleccionrepeticion_afa-0.1.2.dist-info/METADATA
seleccionrepeticion_afa-0.1.2.dist-info/WHEEL
seleccionrepeticion_afa-0.1.2.dist-info/top_level.txt
seleccionrepeticion_afa-0.1.2.dist-info/RECORD
