Metadata-Version: 2.4
Name: SeleccionRepeticion_AFA
Version: 0.1.2
Summary: Librería educativa para jugar con texto: invertir, contar vocales, alternar mayúsculas, etc.
Author: Aitor Fuertes
Requires-Python: >=3.8
